adem/__init__.py
adem/setup.py
adem/arrays/__init__.py
adem/arrays/matrix.py
adem/classes/__init__.py
adem/classes/subclass.py
adem/errors/__init__.py
adem/errors/exceptions.py
adem/fundamentals/__init__.py
adem/fundamentals/primary.py
adem/misc/__init__.py
adem/misc/gen.py
adem/oblects/__init__.py
adem/oblects/states.py
adem/tools/__init__.py
adem/tools/exprs.py
adem-1.0.8.dist-info/LICENSE
adem-1.0.8.dist-info/METADATA
adem-1.0.8.dist-info/WHEEL
adem-1.0.8.dist-info/top_level.txt
adem-1.0.8.dist-info/RECORD
