Metadata-Version: 2.1
Name: adem
Version: 1.0.8
Summary: Giving Python Ability to Work directly on Matrices explicitly
Home-page: https://github.com/miracle5284/adem
Author: Miracle Adebunmi
Author-email: miraclem2014@gmail.com
License: MIT
Platform: UNKNOWN
Classifier: Programming Language :: Python :: 3
Classifier: License :: OSI Approved :: MIT License
Classifier: Operating System :: OS Independent
Requires-Python: >=3.6
Requires-Dist: numpy (>=1.6.0)
